nesteddictionary/__init__.py
nesteddictionary-1.2.2.dist-info/LICENSE
nesteddictionary-1.2.2.dist-info/METADATA
nesteddictionary-1.2.2.dist-info/WHEEL
nesteddictionary-1.2.2.dist-info/top_level.txt
nesteddictionary-1.2.2.dist-info/RECORD
