Metadata-Version: 2.1
Name: nesteddictionary
Version: 1.2.2
Summary: Wrapper for the dict class that extends the functionality for nested dicts including navigating using keypaths and nested key searching. This includes mixed dicts and lists.
Home-page: https://github.com/jacobflanagan/nesteddictionary
Author: Jacob Flanagan
Author-email: flanagan.jacob@gmail.com
Classifier: Programming Language :: Python :: 3
Classifier: License :: OSI Approved :: MIT License
Classifier: Operating System :: OS Independent
Requires-Python: >=3.6
License-File: LICENSE
